smtfuzz/__init__.py
smtfuzz/__main__.py
smtfuzz/smt2_generator.py
smtfuzz/smtfuzz.py
smtfuzz/__pycache__/__main__.cpython-310.pyc
smtfuzz/__pycache__/smtfuzz.cpython-310.pyc
smtfuzz-0.2.dist-info/LICENSE
smtfuzz-0.2.dist-info/METADATA
smtfuzz-0.2.dist-info/WHEEL
smtfuzz-0.2.dist-info/entry_points.txt
smtfuzz-0.2.dist-info/top_level.txt
smtfuzz-0.2.dist-info/RECORD
